{
  "run_id": "2026-02-13",
  "timestamp_utc": "2026-02-13T00:00:00Z",
  "lane": "scout",
  "target": "crates/tokmd-python/src/lib.rs",
  "commands": [
    {
      "cmd": "cargo check -p tokmd-python",
      "exit_code": 0,
      "output_summary": "PASS (Checked tokmd-python v1.5.0)"
    },
    {
      "cmd": "cargo clippy -p tokmd -- -D warnings",
      "exit_code": 0,
      "output_summary": "PASS (Fixed clippy::cloned_ref_to_slice_refs)"
    },
    {
      "cmd": "cargo fmt -- --check",
      "exit_code": 0,
      "output_summary": "PASS (Fixed rustfmt issue)"
    }
  ],
  "results_summary": "Replaced 23 instances of `expect` with `?` in FFI boundary code. Fixed clippy lint and rustfmt issue in `tokmd` crate."
}
