{
  "run_id": "7d373e3b-4ab2-4182-8dc0-be2d829777f2",
  "timestamp_utc": "2026-04-02T12:26:54+00:00",
  "lane": "scout",
  "target": "crates/tokmd-core/tests/error_w70.rs",
  "commands": [
    {
      "cmd": "cargo build --verbose",
      "status": "PASS",
      "summary": "Build successful"
    },
    {
      "cmd": "CI=true cargo test -p tokmd-core --verbose",
      "status": "PASS",
      "summary": "tokmd-core tests pass"
    },
    {
      "cmd": "cargo fmt -- --check",
      "status": "PASS",
      "summary": "Formatting verified"
    },
    {
      "cmd": "cargo clippy -- -D warnings",
      "status": "PASS",
      "summary": "No clippy warnings"
    }
  ],
  "results_summary": "Replaced unwrap_or_default and unwrap with expect in tests"
}
