{
  "run_id": "0d6f0122-2ed5-4e14-aa91-6312d56da6d7",
  "timestamp_utc": "2026-03-30T00:00:00Z",
  "lane": "scout",
  "target": "tokmd-model collect_file_rows Key allocations",
  "proof_method": "bench",
  "commands": [],
  "results": [
    {
      "cmd": "cargo bench",
      "status": "PASS",
      "log": "    Updating crates.io index\n Downloading crates ...\n  Downloaded autocfg v1.5.0\n  Downloaded arbitrary v1.4.2\n  Downloaded serde_spanned v0.6.9\n  Downloaded itoa v1.0.18\n  Downloaded smallvec v1.15.1\n  Downloaded wait-timeout v0.2.1\n  Downloaded zmij v1.0.21\n  Downloaded ucd-trie v0.1.7\n  Downloaded unicode-ident v1.0.24\n  Downloaded proc-macro2 v1.0.106\n  Downloaded serde_json v1.0.149\n  Downloaded toml_edit v0.22.27\n  Downloaded typenum v1.19.0\n  Downloaded tera v1.20.1\n  Downloaded unicode-segmentation v1.12.0\n  Downloaded regex v1.12.3\n  Downloaded proptest v1.11.0\n  Downloaded winnow v0.7.15\n  Downloaded chrono v0.4.44\n  Downloaded clap_builder v4.6.0\n  Downloaded rayon v1.11.0\n  Downloaded zerocopy v0.8.47\n  Downloaded bstr v1.12.1\n  Downloaded libm v0.2.16\n  Downloaded deunicode v1.6.2\n  Downloaded regex-syntax v0.8.10\n  Downloaded chrono-tz v0.9.0\n  Downloaded rustix v1.1.4\n  Downloaded hashbrown v0.14.5\n  Downloaded pest v2.8.6\n  Downloaded hashbrown v0.16.1\n  Downloaded aho-corasick v1.1.4\n  Downloaded syn v2.0.117\n  Downloaded itertools v0.11.0\n  Downloaded insta v1.47.0\n  Downloaded indexmap v2.13.0\n  Downloaded rand v0.9.2\n  Downloaded rand v0.8.5\n  Downloaded regex-automata v0.4.14\n  Downloaded memchr v2.8.0\n  Downloaded crossbeam-channel v0.5.15\n  Downloaded parse-zoneinfo v0.3.1\n  Downloaded ignore v0.4.25\n  Downloaded getrandom v0.3.4\n  Downloaded toml v0.8.23\n  Downloaded tokei v14.0.0\n  Downloaded tempfile v3.27.0\n  Downloaded serde_derive v1.0.228\n  Downloaded serde_core v1.0.228\n  Downloaded libc v0.2.183\n  Downloaded serde v1.0.228\n  Downloaded rayon-core v1.13.0\n  Downloaded pest_meta v2.8.6\n  Downloaded log v0.4.29\n  Downloaded grep-searcher v0.1.16\n  Downloaded getrandom v0.4.2\n  Downloaded clap v4.6.0\n  Downloaded thiserror-impl v1.0.69\n  Downloaded thiserror v1.0.69\n  Downloaded pest_generator v2.8.6\n  Downloaded pest_derive v2.8.6\n  Downloaded parking_lot_core v0.9.12\n  Downloaded parking_lot v0.12.5\n  Downloaded once_cell v1.21.4\n  Downloaded num-traits v0.2.19\n  Downloaded memmap2 v0.9.10\n  Downloaded iana-time-zone v0.1.65\n  Downloaded getrandom v0.2.17\n  Downloaded equivalent v1.0.2\n  Downloaded dashmap v6.1.0\n  Downloaded crossbeam-utils v0.8.21\n  Downloaded crossbeam-epoch v0.9.18\n  Downloaded console v0.16.3\n  Downloaded colored v2.2.0\n  Downloaded clap_derive v4.6.0\n  Downloaded walkdir v2.5.0\n  Downloaded toml_write v0.1.2\n  Downloaded toml_datetime v0.6.11\n  Downloaded term_size v0.3.2\n  Downloaded table_formatter v0.6.1\n  Downloaded encoding_rs v0.8.35\n  Downloaded sha2 v0.10.9\n  Downloaded rusty-fork v0.3.1\n  Downloaded rand_core v0.9.5\n  Downloaded rand_core v0.6.4\n  Downloaded quote v1.0.45\n  Downloaded ppv-lite86 v0.2.21\n  Downloaded phf v0.11.3\n  Downloaded lock_api v0.4.14\n  Downloaded grep-matcher v0.1.8\n  Downloaded globwalk v0.9.1\n  Downloaded globset v0.4.18\n  Downloaded encoding_rs_io v0.1.7\n  Downloaded either v1.15.0\n  Downloaded digest v0.10.7\n  Downloaded crossbeam-deque v0.8.6\n  Downloaded clap_lex v1.1.0\n  Downloaded clap-cargo v0.18.3\n  Downloaded chrono-tz-build v0.3.0\n  Downloaded version_check v0.9.5\n  Downloaded unarray v0.1.4\n  Downloaded slug v0.1.6\n  Downloaded siphasher v1.0.2\n  Downloaded scopeguard v1.2.0\n  Downloaded same-file v1.0.6\n  Downloaded rand_xorshift v0.4.0\n  Downloaded rand_chacha v0.9.0\n  Downloaded phf_shared v0.11.3\n  Downloaded phf_codegen v0.11.3\n  Downloaded lazy_static v1.5.0\n  Downloaded fnv v1.0.7\n  Downloaded fastrand v2.3.0\n  Downloaded etcetera v0.8.0\n  Downloaded cfg-if v1.0.4\n  Downloaded similar v2.7.0\n  Downloaded rand_chacha v0.3.1\n  Downloaded quick-error v1.2.3\n  Downloaded phf_generator v0.11.3\n  Downloaded percent-encoding v2.3.2\n  Downloaded json5 v0.4.1\n  Downloaded humansize v2.1.3\n  Downloaded heck v0.5.0\n  Downloaded errno v0.3.14\n  Downloaded derive_arbitrary v1.4.2\n  Downloaded generic-array v0.14.7\n  Downloaded crypto-common v0.1.7\n  Downloaded cpufeatures v0.2.17\n  Downloaded bitflags v2.11.0\n  Downloaded bit-vec v0.8.0\n  Downloaded anstyle v1.0.14\n  Downloaded block-buffer v0.10.4\n  Downloaded bit-set v0.8.0\n  Downloaded linux-raw-sys v0.12.1\nerror: no bench target named `collect_bench` in `tokmd-model` package"
    },
    {
      "cmd": "cargo test",
      "status": "PASS",
      "log": "test snapshot_empty_lang_report ... ok\ntest snapshot_lang_report_collapse_shape ... ok\ntest snapshot_file_rows_separate ... ok\ntest snapshot_lang_report_separate_shape ... ok\ntest snapshot_lang_report_top1 ... ok\ntest snapshot_module_report_shape ... ok\n\ntest result: ok. 9 passed; 0 failed; 0 ignored; 0 measured; 0 filtered out; finished in 0.20s\n\n   Doc-tests tokmd_model\n     Running `/home/jules/.rustup/toolchains/stable-x86_64-unknown-linux-gnu/bin/rustdoc --edition=2024 --crate-type lib --color auto --crate-name tokmd_model --test crates/tokmd-model/src/lib.rs --test-run-directory /app/crates/tokmd-model --extern insta=/app/target/debug/deps/libinsta-c8c228f513c5db22.rlib --extern proptest=/app/target/debug/deps/libproptest-a5383cea6f59b512.rlib --extern serde=/app/target/debug/deps/libserde-8fb549f2c4607764.rlib --extern serde_json=/app/target/debug/deps/libserde_json-a890abff865443e4.rlib --extern tempfile=/app/target/debug/deps/libtempfile-f51a2aafe76acb83.rlib --extern tokei=/app/target/debug/deps/libtokei-f4a5f33a9fe4dc46.rlib --extern tokmd_model=/app/target/debug/deps/libtokmd_model-69f224289d1ec1a8.rlib --extern tokmd_module_key=/app/target/debug/deps/libtokmd_module_key-1e11ee2ab967eae0.rlib --extern tokmd_types=/app/target/debug/deps/libtokmd_types-2404b7b73455ad21.rlib -L dependency=/app/target/debug/deps -C embed-bitcode=no --check-cfg 'cfg(docsrs,test)' --check-cfg 'cfg(feature, values())' --error-format human`\n\nrunning 3 tests\ntest crates/tokmd-model/src/lib.rs - module_key (line 833) ... ok\ntest crates/tokmd-model/src/lib.rs - avg (line 723) ... ok\ntest crates/tokmd-model/src/lib.rs - normalize_path (line 748) ... ok\n\ntest result: ok. 3 passed; 0 failed; 0 ignored; 0 measured; 0 filtered out; finished in 0.00s\n\nall doctests ran in 0.56s; merged doctests compilation took 0.54s"
    },
    {
      "cmd": "cargo build",
      "status": "PASS",
      "log": "   Compiling tokmd-badge v1.9.0 (/app/crates/tokmd-badge)\n     Running `/home/jules/.rustup/toolchains/stable-x86_64-unknown-linux-gnu/bin/rustc --crate-name tokmd_badge --edition=2024 crates/tokmd-badge/src/lib.rs --error-format=json --json=diagnostic-rendered-ansi,artifacts,future-incompat --crate-type lib --emit=dep-info,metadata,link -C embed-bitcode=no -C debuginfo=2 --check-cfg 'cfg(docsrs,test)' --check-cfg 'cfg(feature, values())' -C metadata=e9b9c79b517d4826 -C extra-filename=-cea25afdb76d8de5 --out-dir /app/target/debug/deps -C incremental=/app/target/debug/incremental -L dependency=/app/target/debug/deps`\n   Compiling tokmd-analysis-explain v1.9.0 (/app/crates/tokmd-analysis-explain)\n     Running `/home/jules/.rustup/toolchains/stable-x86_64-unknown-linux-gnu/bin/rustc --crate-name tokmd_analysis_explain --edition=2024 crates/tokmd-analysis-explain/src/lib.rs --error-format=json --json=diagnostic-rendered-ansi,artifacts,future-incompat --crate-type lib --emit=dep-info,metadata,link -C embed-bitcode=no -C debuginfo=2 --check-cfg 'cfg(docsrs,test)' --check-cfg 'cfg(feature, values())' -C metadata=29d7713800597330 -C extra-filename=-f555c7f62f539207 --out-dir /app/target/debug/deps -C incremental=/app/target/debug/incremental -L dependency=/app/target/debug/deps`\n   Compiling tokmd v1.9.0 (/app/crates/tokmd)\n     Running `/home/jules/.rustup/toolchains/stable-x86_64-unknown-linux-gnu/bin/rustc --crate-name tokmd --edition=2024 crates/tokmd/src/lib.rs --error-format=json --json=diagnostic-rendered-ansi,artifacts,future-incompat --crate-type lib --emit=dep-info,metadata,link -C embed-bitcode=no -C debuginfo=2 --cfg 'feature=\"archetype\"' --cfg 'feature=\"content\"' --cfg 'feature=\"default\"' --cfg 'feature=\"fun\"' --cfg 'feature=\"git\"' --cfg 'feature=\"topics\"' --cfg 'feature=\"ui\"' --cfg 'feature=\"walk\"' --check-cfg 'cfg(docsrs,test)' --check-cfg 'cfg(feature, values(\"alias-tok\", \"archetype\", \"content\", \"default\", \"fun\", \"git\", \"topics\", \"ui\", \"walk\"))' -C metadata=2439a452d11f98e7 -C extra-filename=-4e32883fe1348d35 --out-dir /app/target/debug/deps -C incremental=/app/target/debug/incremental -L dependency=/app/target/debug/deps --extern anyhow=/app/target/debug/deps/libanyhow-1c897acad9a38b79.rmeta --extern blake3=/app/target/debug/deps/libblake3-ba57c91f91dea2f8.rmeta --extern clap=/app/target/debug/deps/libclap-4becc75c6d6358cd.rmeta --extern clap_complete=/app/target/debug/deps/libclap_complete-db4fc26ed995b904.rmeta --extern console=/app/target/debug/deps/libconsole-082fb92185463311.rmeta --extern dialoguer=/app/target/debug/deps/libdialoguer-21a6fbd0d024b082.rmeta --extern dirs=/app/target/debug/deps/libdirs-e2cb4f3a84b5aae4.rmeta --extern serde=/app/target/debug/deps/libserde-7b496471ddbe204c.rmeta --extern serde_json=/app/target/debug/deps/libserde_json-02554ac7efa4e2d5.rmeta --extern time=/app/target/debug/deps/libtime-ff5916d77934ff1e.rmeta --extern tokmd_analysis=/app/target/debug/deps/libtokmd_analysis-a100ab74b8f83e3f.rmeta --extern tokmd_analysis_explain=/app/target/debug/deps/libtokmd_analysis_explain-f555c7f62f539207.rmeta --extern tokmd_analysis_format=/app/target/debug/deps/libtokmd_analysis_format-fcd662b0a272e5cf.rmeta --extern tokmd_analysis_grid=/app/target/debug/deps/libtokmd_analysis_grid-b975859fd6ce769f.rmeta --extern tokmd_analysis_types=/app/target/debug/deps/libtokmd_analysis_types-a2119101128c1acf.rmeta --extern tokmd_badge=/app/target/debug/deps/libtokmd_badge-cea25afdb76d8de5.rmeta --extern tokmd_cockpit=/app/target/debug/deps/libtokmd_cockpit-cce84232adc64254.rmeta --extern tokmd_config=/app/target/debug/deps/libtokmd_config-996360d4ac8a6cfd.rmeta --extern tokmd_context_git=/app/target/debug/deps/libtokmd_context_git-b44d4dcb405a7dfa.rmeta --extern tokmd_context_policy=/app/target/debug/deps/libtokmd_context_policy-408c25833e79ac21.rmeta --extern tokmd_envelope=/app/target/debug/deps/libtokmd_envelope-f814661ecaa9d5a5.rmeta --extern tokmd_exclude=/app/target/debug/deps/libtokmd_exclude-4e503ec45eb7d506.rmeta --extern tokmd_export_tree=/app/target/debug/deps/libtokmd_export_tree-c1edb628bf303e61.rmeta --extern tokmd_format=/app/target/debug/deps/libtokmd_format-90b640945e61b2c1.rmeta --extern tokmd_gate=/app/target/debug/deps/libtokmd_gate-6bf8c0497d5f4a8d.rmeta --extern tokmd_git=/app/target/debug/deps/libtokmd_git-c7d6904f0b14a52f.rmeta --extern tokmd_model=/app/target/debug/deps/libtokmd_model-de4429ef2fd572ba.rmeta --extern tokmd_path=/app/target/debug/deps/libtokmd_path-7ed92164034bee00.rmeta --extern tokmd_progress=/app/target/debug/deps/libtokmd_progress-6493af3ed09d71d8.rmeta --extern tokmd_scan=/app/target/debug/deps/libtokmd_scan-c818da9d672267c5.rmeta --extern tokmd_settings=/app/target/debug/deps/libtokmd_settings-9edc796d5b2c7921.rmeta --extern tokmd_tokeignore=/app/target/debug/deps/libtokmd_tokeignore-cd4f92ff80c5d054.rmeta --extern tokmd_tool_schema=/app/target/debug/deps/libtokmd_tool_schema-43612909d26a540b.rmeta --extern tokmd_types=/app/target/debug/deps/libtokmd_types-1a256f6860a92825.rmeta --extern toml=/app/target/debug/deps/libtoml-416a762657a99d87.rmeta -L native=/app/target/debug/build/blake3-12e682763928d5d8/out -L native=/app/target/debug/build/blake3-12e682763928d5d8/out`\n   Compiling tokmd-substrate v1.9.0 (/app/crates/tokmd-substrate)\n     Running `/home/jules/.rustup/toolchains/stable-x86_64-unknown-linux-gnu/bin/rustc --crate-name tokmd_substrate --edition=2024 crates/tokmd-substrate/src/lib.rs --error-format=json --json=diagnostic-rendered-ansi,artifacts,future-incompat --crate-type lib --emit=dep-info,metadata,link -C embed-bitcode=no -C debuginfo=2 --check-cfg 'cfg(docsrs,test)' --check-cfg 'cfg(feature, values())' -C metadata=ca4b2677fbc23b13 -C extra-filename=-2a0628830ad77d63 --out-dir /app/target/debug/deps -C incremental=/app/target/debug/incremental -L dependency=/app/target/debug/deps --extern serde=/app/target/debug/deps/libserde-7b496471ddbe204c.rmeta`\n   Compiling base64 v0.22.1\n     Running `/home/jules/.rustup/toolchains/stable-x86_64-unknown-linux-gnu/bin/rustc --crate-name base64 --edition=2018 /home/jules/.cargo/registry/src/index.crates.io-1949cf8c6b5b557f/base64-0.22.1/src/lib.rs --error-format=json --json=diagnostic-rendered-ansi,artifacts,future-incompat --crate-type lib --emit=dep-info,metadata,link -C embed-bitcode=no -C debuginfo=2 --cfg 'feature=\"alloc\"' --cfg 'feature=\"default\"' --cfg 'feature=\"std\"' --check-cfg 'cfg(docsrs,test)' --check-cfg 'cfg(feature, values(\"alloc\", \"default\", \"std\"))' -C metadata=df93e3f3db1105f2 -C extra-filename=-5ec41e4236db44dc --out-dir /app/target/debug/deps -L dependency=/app/target/debug/deps --cap-lints allow`\n   Compiling tokmd-sensor v1.9.0 (/app/crates/tokmd-sensor)\n     Running `/home/jules/.rustup/toolchains/stable-x86_64-unknown-linux-gnu/bin/rustc --crate-name tokmd_sensor --edition=2024 crates/tokmd-sensor/src/lib.rs --error-format=json --json=diagnostic-rendered-ansi,artifacts,future-incompat --crate-type lib --emit=dep-info,metadata,link -C embed-bitcode=no -C debuginfo=2 --cfg 'feature=\"default\"' --check-cfg 'cfg(docsrs,test)' --check-cfg 'cfg(feature, values(\"default\"))' -C metadata=db727498d8b25f96 -C extra-filename=-d305e98a22eeebca --out-dir /app/target/debug/deps -C incremental=/app/target/debug/incremental -L dependency=/app/target/debug/deps --extern anyhow=/app/target/debug/deps/libanyhow-1c897acad9a38b79.rmeta --extern serde=/app/target/debug/deps/libserde-7b496471ddbe204c.rmeta --extern tokmd_envelope=/app/target/debug/deps/libtokmd_envelope-f814661ecaa9d5a5.rmeta --extern tokmd_model=/app/target/debug/deps/libtokmd_model-de4429ef2fd572ba.rmeta --extern tokmd_scan=/app/target/debug/deps/libtokmd_scan-c818da9d672267c5.rmeta --extern tokmd_settings=/app/target/debug/deps/libtokmd_settings-9edc796d5b2c7921.rmeta --extern tokmd_substrate=/app/target/debug/deps/libtokmd_substrate-2a0628830ad77d63.rmeta --extern tokmd_types=/app/target/debug/deps/libtokmd_types-1a256f6860a92825.rmeta -L native=/app/target/debug/build/blake3-12e682763928d5d8/out -L native=/app/target/debug/build/blake3-12e682763928d5d8/out`\n   Compiling tokmd-core v1.9.0 (/app/crates/tokmd-core)\n     Running `/home/jules/.rustup/toolchains/stable-x86_64-unknown-linux-gnu/bin/rustc --crate-name tokmd_core --edition=2024 crates/tokmd-core/src/lib.rs --error-format=json --json=diagnostic-rendered-ansi,artifacts,future-incompat --crate-type lib --emit=dep-info,metadata,link -C embed-bitcode=no -C debuginfo=2 --cfg 'feature=\"default\"' --check-cfg 'cfg(docsrs,test)' --check-cfg 'cfg(feature, values(\"analysis\", \"cockpit\", \"default\", \"tokmd-analysis-types\"))' -C metadata=fa20c5b0243b991f -C extra-filename=-70e3e5a55ada1b60 --out-dir /app/target/debug/deps -C incremental=/app/target/debug/incremental -L dependency=/app/target/debug/deps --extern anyhow=/app/target/debug/deps/libanyhow-1c897acad9a38b79.rmeta --extern base64=/app/target/debug/deps/libbase64-5ec41e4236db44dc.rmeta --extern serde=/app/target/debug/deps/libserde-7b496471ddbe204c.rmeta --extern serde_json=/app/target/debug/deps/libserde_json-02554ac7efa4e2d5.rmeta --extern tokmd_config=/app/target/debug/deps/libtokmd_config-996360d4ac8a6cfd.rmeta --extern tokmd_format=/app/target/debug/deps/libtokmd_format-90b640945e61b2c1.rmeta --extern tokmd_model=/app/target/debug/deps/libtokmd_model-de4429ef2fd572ba.rmeta --extern tokmd_scan=/app/target/debug/deps/libtokmd_scan-c818da9d672267c5.rmeta --extern tokmd_scan_args=/app/target/debug/deps/libtokmd_scan_args-4084729957dff692.rmeta --extern tokmd_settings=/app/target/debug/deps/libtokmd_settings-9edc796d5b2c7921.rmeta --extern tokmd_types=/app/target/debug/deps/libtokmd_types-1a256f6860a92825.rmeta -L native=/app/target/debug/build/blake3-12e682763928d5d8/out -L native=/app/target/debug/build/blake3-12e682763928d5d8/out`\n   Compiling tokmd-analysis-halstead v1.9.0 (/app/crates/tokmd-analysis-halstead)\n     Running `/home/jules/.rustup/toolchains/stable-x86_64-unknown-linux-gnu/bin/rustc --crate-name tokmd_analysis_halstead --edition=2024 crates/tokmd-analysis-halstead/src/lib.rs --error-format=json --json=diagnostic-rendered-ansi,artifacts,future-incompat --crate-type lib --emit=dep-info,metadata,link -C embed-bitcode=no -C debuginfo=2 --check-cfg 'cfg(docsrs,test)' --check-cfg 'cfg(feature, values())' -C metadata=e58742106370dc7f -C extra-filename=-6cdc594b46d9d631 --out-dir /app/target/debug/deps -C incremental=/app/target/debug/incremental -L dependency=/app/target/debug/deps --extern anyhow=/app/target/debug/deps/libanyhow-1c897acad9a38b79.rmeta --extern tokmd_analysis_types=/app/target/debug/deps/libtokmd_analysis_types-a2119101128c1acf.rmeta --extern tokmd_analysis_util=/app/target/debug/deps/libtokmd_analysis_util-e7948523546f7be5.rmeta --extern tokmd_content=/app/target/debug/deps/libtokmd_content-9d678f1ee4ef3b0a.rmeta --extern tokmd_types=/app/target/debug/deps/libtokmd_types-1a256f6860a92825.rmeta -L native=/app/target/debug/build/blake3-12e682763928d5d8/out -L native=/app/target/debug/build/blake3-12e682763928d5d8/out`\n   Compiling tokmd-ffi-envelope v1.9.0 (/app/crates/tokmd-ffi-envelope)\n     Running `/home/jules/.rustup/toolchains/stable-x86_64-unknown-linux-gnu/bin/rustc --crate-name tokmd_ffi_envelope --edition=2024 crates/tokmd-ffi-envelope/src/lib.rs --error-format=json --json=diagnostic-rendered-ansi,artifacts,future-incompat --crate-type lib --emit=dep-info,metadata,link -C embed-bitcode=no -C debuginfo=2 --check-cfg 'cfg(docsrs,test)' --check-cfg 'cfg(feature, values())' -C metadata=9d1d85d127057701 -C extra-filename=-bab5144772226f49 --out-dir /app/target/debug/deps -C incremental=/app/target/debug/incremental -L dependency=/app/target/debug/deps --extern serde_json=/app/target/debug/deps/libserde_json-02554ac7efa4e2d5.rmeta`\n     Running `/home/jules/.rustup/toolchains/stable-x86_64-unknown-linux-gnu/bin/rustc --crate-name tokmd --edition=2024 crates/tokmd/src/bin/tokmd.rs --error-format=json --json=diagnostic-rendered-ansi,artifacts,future-incompat --crate-type bin --emit=dep-info,link -C embed-bitcode=no -C debuginfo=2 --cfg 'feature=\"archetype\"' --cfg 'feature=\"content\"' --cfg 'feature=\"default\"' --cfg 'feature=\"fun\"' --cfg 'feature=\"git\"' --cfg 'feature=\"topics\"' --cfg 'feature=\"ui\"' --cfg 'feature=\"walk\"' --check-cfg 'cfg(docsrs,test)' --check-cfg 'cfg(feature, values(\"alias-tok\", \"archetype\", \"content\", \"default\", \"fun\", \"git\", \"topics\", \"ui\", \"walk\"))' -C metadata=7ed44a30fca95812 -C extra-filename=-4d89631356d65acc --out-dir /app/target/debug/deps -C incremental=/app/target/debug/incremental -L dependency=/app/target/debug/deps --extern anyhow=/app/target/debug/deps/libanyhow-1c897acad9a38b79.rlib --extern blake3=/app/target/debug/deps/libblake3-ba57c91f91dea2f8.rlib --extern clap=/app/target/debug/deps/libclap-4becc75c6d6358cd.rlib --extern clap_complete=/app/target/debug/deps/libclap_complete-db4fc26ed995b904.rlib --extern console=/app/target/debug/deps/libconsole-082fb92185463311.rlib --extern dialoguer=/app/target/debug/deps/libdialoguer-21a6fbd0d024b082.rlib --extern dirs=/app/target/debug/deps/libdirs-e2cb4f3a84b5aae4.rlib --extern serde=/app/target/debug/deps/libserde-7b496471ddbe204c.rlib --extern serde_json=/app/target/debug/deps/libserde_json-02554ac7efa4e2d5.rlib --extern time=/app/target/debug/deps/libtime-ff5916d77934ff1e.rlib --extern tokmd=/app/target/debug/deps/libtokmd-4e32883fe1348d35.rlib --extern tokmd_analysis=/app/target/debug/deps/libtokmd_analysis-a100ab74b8f83e3f.rlib --extern tokmd_analysis_explain=/app/target/debug/deps/libtokmd_analysis_explain-f555c7f62f539207.rlib --extern tokmd_analysis_format=/app/target/debug/deps/libtokmd_analysis_format-fcd662b0a272e5cf.rlib --extern tokmd_analysis_grid=/app/target/debug/deps/libtokmd_analysis_grid-b975859fd6ce769f.rlib --extern tokmd_analysis_types=/app/target/debug/deps/libtokmd_analysis_types-a2119101128c1acf.rlib --extern tokmd_badge=/app/target/debug/deps/libtokmd_badge-cea25afdb76d8de5.rlib --extern tokmd_cockpit=/app/target/debug/deps/libtokmd_cockpit-cce84232adc64254.rlib --extern tokmd_config=/app/target/debug/deps/libtokmd_config-996360d4ac8a6cfd.rlib --extern tokmd_context_git=/app/target/debug/deps/libtokmd_context_git-b44d4dcb405a7dfa.rlib --extern tokmd_context_policy=/app/target/debug/deps/libtokmd_context_policy-408c25833e79ac21.rlib --extern tokmd_envelope=/app/target/debug/deps/libtokmd_envelope-f814661ecaa9d5a5.rlib --extern tokmd_exclude=/app/target/debug/deps/libtokmd_exclude-4e503ec45eb7d506.rlib --extern tokmd_export_tree=/app/target/debug/deps/libtokmd_export_tree-c1edb628bf303e61.rlib --extern tokmd_format=/app/target/debug/deps/libtokmd_format-90b640945e61b2c1.rlib --extern tokmd_gate=/app/target/debug/deps/libtokmd_gate-6bf8c0497d5f4a8d.rlib --extern tokmd_git=/app/target/debug/deps/libtokmd_git-c7d6904f0b14a52f.rlib --extern tokmd_model=/app/target/debug/deps/libtokmd_model-de4429ef2fd572ba.rlib --extern tokmd_path=/app/target/debug/deps/libtokmd_path-7ed92164034bee00.rlib --extern tokmd_progress=/app/target/debug/deps/libtokmd_progress-6493af3ed09d71d8.rlib --extern tokmd_scan=/app/target/debug/deps/libtokmd_scan-c818da9d672267c5.rlib --extern tokmd_settings=/app/target/debug/deps/libtokmd_settings-9edc796d5b2c7921.rlib --extern tokmd_tokeignore=/app/target/debug/deps/libtokmd_tokeignore-cd4f92ff80c5d054.rlib --extern tokmd_tool_schema=/app/target/debug/deps/libtokmd_tool_schema-43612909d26a540b.rlib --extern tokmd_types=/app/target/debug/deps/libtokmd_types-1a256f6860a92825.rlib --extern toml=/app/target/debug/deps/libtoml-416a762657a99d87.rlib -L native=/app/target/debug/build/blake3-12e682763928d5d8/out -L native=/app/target/debug/build/blake3-12e682763928d5d8/out`\n    Finished `dev` profile [unoptimized + debuginfo] target(s) in 44.07s"
    },
    {
      "cmd": "cargo fmt",
      "status": "PASS",
      "log": ""
    },
    {
      "cmd": "cargo clippy",
      "status": "PASS",
      "log": "    Checking memchr v2.8.0\n    Checking serde_core v1.0.228\n    Checking utf8parse v0.2.2\n    Checking cfg-if v1.0.4\n    Checking anstyle v1.0.14\n    Checking anstyle-parse v1.0.0\n    Checking is_terminal_polyfill v1.70.2\n    Checking colorchoice v1.0.5\n    Checking anstyle-query v1.1.5\n    Checking strsim v0.11.1\n    Checking anstream v1.0.0\n    Checking clap_lex v1.1.0\n    Checking itoa v1.0.18\n    Checking zmij v1.0.21\n    Checking clap_builder v4.6.0\n    Checking constant_time_eq v0.4.2\n    Checking arrayref v0.3.9\n    Checking cpufeatures v0.2.17\n    Checking arrayvec v0.7.6\n    Checking anyhow v1.0.102\n    Checking blake3 v1.8.3\n    Checking libc v0.2.183\n    Checking aho-corasick v1.1.4\n    Checking clap v4.6.0\n    Checking serde v1.0.228\n    Checking serde_json v1.0.149\n    Checking regex-syntax v0.8.10\n    Checking crossbeam-utils v0.8.21\n    Checking tokmd-types v1.9.0 (/app/crates/tokmd-types)\n    Checking tokmd-envelope v1.9.0 (/app/crates/tokmd-envelope)\n    Checking regex-automata v0.4.14\n   Compiling getrandom v0.2.17\n    Checking crossbeam-epoch v0.9.18\n    Checking crossbeam-deque v0.8.6\n   Compiling rand_core v0.6.4\n   Compiling rand_chacha v0.3.1\n   Compiling rand v0.8.5\n    Checking bstr v1.12.1\n    Checking log v0.4.29\n   Compiling phf_generator v0.11.3\n    Checking regex v1.12.3\n   Compiling pest v2.8.6\n    Checking tokmd-analysis-types v1.9.0 (/app/crates/tokmd-analysis-types)\n   Compiling phf_codegen v0.11.3\n    Checking globset v0.4.18\n    Checking same-file v1.0.6\n    Checking walkdir v2.5.0\n   Compiling pest_meta v2.8.6\n   Compiling parse-zoneinfo v0.3.1\n   Compiling chrono-tz-build v0.3.0\n    Checking either v1.15.0\n    Checking winnow v1.0.0\n    Checking tokmd-math v1.9.0 (/app/crates/tokmd-math)\n   Compiling chrono-tz v0.9.0\n    Checking toml_parser v1.0.10+spec-1.1.0\n   Compiling pest_generator v2.8.6\n    Checking ignore v0.4.25\n    Checking toml_datetime v1.0.1+spec-1.1.0\n    Checking serde_spanned v1.0.4\n    Checking toml_writer v1.0.7+spec-1.1.0\n   Compiling pest_derive v2.8.6\n    Checking toml v1.0.7+spec-1.1.0\n    Checking tokmd-analysis-util v1.9.0 (/app/crates/tokmd-analysis-util)\n    Checking rayon-core v1.13.0\n   Compiling globwalk v0.9.1\n    Checking rayon v1.11.0\n    Checking once_cell v1.21.4\n    Checking equivalent v1.0.2\n   Compiling lazy_static v1.5.0\n    Checking scopeguard v1.2.0\n    Checking smallvec v1.15.1\n    Checking hashbrown v0.16.1\n    Checking parking_lot_core v0.9.12\n    Checking lock_api v0.4.14\n    Checking getrandom v0.4.2\n    Checking tokmd-settings v1.9.0 (/app/crates/tokmd-settings)\n    Checking indexmap v2.13.0\n   Compiling json5 v0.4.1\n    Checking tokmd-content v1.9.0 (/app/crates/tokmd-content)\n    Checking toml_datetime v0.6.11\n    Checking serde_spanned v0.6.9\n    Checking encoding_rs v0.8.35\n   Compiling tera v1.20.1\n   Compiling num-conv v0.2.0\n    Checking winnow v0.7.15\n    Checking toml_write v0.1.2\n    Checking powerfmt v0.2.0\n   Compiling time-core v0.1.8\n    Checking colored v2.2.0\n   Compiling time-macros v0.2.27\n    Checking encoding_rs_io v0.1.7\n    Checking deranged v0.5.8\n    Checking toml_edit v0.22.27\n    Checking thiserror v1.0.69\n    Checking itertools v0.11.0\n    Checking tokmd-git v1.9.0 (/app/crates/tokmd-git)\n    Checking memmap2 v0.9.10\n    Checking grep-matcher v0.1.8\n    Checking hashbrown v0.14.5\n    Checking tokmd-path v1.9.0 (/app/crates/tokmd-path)\n    Checking linux-raw-sys v0.12.1\n    Checking bitflags v2.11.0\n    Checking home v0.5.12 (/app/vendor/home-0.5.12)\n    Checking etcetera v0.8.0\n    Checking time v0.3.47\n    Checking rustix v1.1.4\n    Checking toml v0.8.23\n    Checking dashmap v6.1.0\n    Checking table_formatter v0.6.1\n    Checking arbitrary v1.4.2\n    Checking grep-searcher v0.1.16\n   Compiling tokei v14.0.0\n    Checking parking_lot v0.12.5\n    Checking crossbeam-channel v0.5.15\n    Checking term_size v0.3.2\n    Checking clap-cargo v0.18.3\n    Checking fastrand v2.3.0\n    Checking tokmd-io-port v1.9.0 (/app/crates/tokmd-io-port)\n    Checking tempfile v3.27.0\n    Checking unicode-width v0.2.2\n    Checking tokmd-walk v1.9.0 (/app/crates/tokmd-walk)\n    Checking tokmd-tool-schema v1.9.0 (/app/crates/tokmd-tool-schema)\n    Checking tokmd-redact v1.9.0 (/app/crates/tokmd-redact)\n    Checking console v0.16.3\n    Checking csv-core v0.1.13\n    Checking ryu v1.0.23\n    Checking tokmd-module-key v1.9.0 (/app/crates/tokmd-module-key)\n    Checking csv v1.4.0\n    Checking tokmd-config v1.9.0 (/app/crates/tokmd-config)\n    Checking tokmd-scan-args v1.9.0 (/app/crates/tokmd-scan-args)\n    Checking portable-atomic v1.13.1\n    Checking midly v0.5.3\n    Checking uuid v1.22.0\n    Checking tokmd-analysis-maintainability v1.9.0 (/app/crates/tokmd-analysis-maintainability)\n    Checking tokmd-export-tree v1.9.0 (/app/crates/tokmd-export-tree)\n    Checking tokmd-scan v1.9.0 (/app/crates/tokmd-scan)\n    Checking tokmd-model v1.9.0 (/app/crates/tokmd-model)\n    Checking tokmd-analysis-imports v1.9.0 (/app/crates/tokmd-analysis-imports)\n    Checking rustc-hash v2.1.1\n    Checking unit-prefix v0.5.2\n    Checking option-ext v0.2.0\n    Checking dirs-sys v0.5.0\n    Checking indicatif v0.18.4\n    Checking tokmd-analysis-near-dup v1.9.0 (/app/crates/tokmd-analysis-near-dup)\n    Checking tokmd-analysis-content v1.9.0 (/app/crates/tokmd-analysis-content)\n    Checking tokmd-fun v1.9.0 (/app/crates/tokmd-fun)\n    Checking tokmd-analysis-derived v1.9.0 (/app/crates/tokmd-analysis-derived)\n    Checking tokmd-analysis-complexity v1.9.0 (/app/crates/tokmd-analysis-complexity)\n    Checking tokmd-format v1.9.0 (/app/crates/tokmd-format)\n    Checking tokmd-analysis-license v1.9.0 (/app/crates/tokmd-analysis-license)\n    Checking tokmd-analysis-assets v1.9.0 (/app/crates/tokmd-analysis-assets)\n    Checking tokmd-analysis-html v1.9.0 (/app/crates/tokmd-analysis-html)\n    Checking tokmd-analysis-git v1.9.0 (/app/crates/tokmd-analysis-git)\n    Checking tokmd-analysis-fingerprint v1.9.0 (/app/crates/tokmd-analysis-fingerprint)\n    Checking tokmd-analysis-effort v1.9.0 (/app/crates/tokmd-analysis-effort)\n    Checking tokmd-analysis-api-surface v1.9.0 (/app/crates/tokmd-analysis-api-surface)\n    Checking tokmd-analysis-entropy v1.9.0 (/app/crates/tokmd-analysis-entropy)\n    Checking tokmd-analysis-archetype v1.9.0 (/app/crates/tokmd-analysis-archetype)\n    Checking tokmd-analysis-fun v1.9.0 (/app/crates/tokmd-analysis-fun)\n    Checking tokmd-analysis-topics v1.9.0 (/app/crates/tokmd-analysis-topics)\n    Checking tokmd-analysis-grid v1.9.0 (/app/crates/tokmd-analysis-grid)\n    Checking zeroize v1.8.2\n    Checking shell-words v1.1.1\n    Checking tokmd-tokeignore v1.9.0 (/app/crates/tokmd-tokeignore)\n    Checking tokmd-analysis-format v1.9.0 (/app/crates/tokmd-analysis-format)\n    Checking tokmd-analysis v1.9.0 (/app/crates/tokmd-analysis)\n    Checking dialoguer v0.12.0\n    Checking tokmd-progress v1.9.0 (/app/crates/tokmd-progress)\n    Checking dirs v6.0.0\n    Checking tokmd-cockpit v1.9.0 (/app/crates/tokmd-cockpit)\n    Checking tokmd-exclude v1.9.0 (/app/crates/tokmd-exclude)\n    Checking tokmd-context-git v1.9.0 (/app/crates/tokmd-context-git)\n    Checking tokmd-context-policy v1.9.0 (/app/crates/tokmd-context-policy)\n    Checking tokmd-gate v1.9.0 (/app/crates/tokmd-gate)\n    Checking clap_complete v4.6.0\n    Checking tokmd-badge v1.9.0 (/app/crates/tokmd-badge)\n    Checking tokmd-analysis-explain v1.9.0 (/app/crates/tokmd-analysis-explain)\n    Checking tokmd-substrate v1.9.0 (/app/crates/tokmd-substrate)\n    Checking base64 v0.22.1\n    Checking tokmd-sensor v1.9.0 (/app/crates/tokmd-sensor)\n    Checking tokmd-core v1.9.0 (/app/crates/tokmd-core)\n    Checking tokmd-analysis-halstead v1.9.0 (/app/crates/tokmd-analysis-halstead)\n    Checking tokmd-ffi-envelope v1.9.0 (/app/crates/tokmd-ffi-envelope)\n    Checking tokmd v1.9.0 (/app/crates/tokmd)\n    Finished `dev` profile [unoptimized + debuginfo] target(s) in 30.31s"
    },
    {
      "cmd": "cargo bench",
      "status": "PASS",
      "log": "Gnuplot not found, using plotters backend\nBenchmarking collect_file_rows_10000\nBenchmarking collect_file_rows_10000: Warming up for 3.0000 s\nBenchmarking collect_file_rows_10000: Collecting 100 samples in estimated 7.2853 s (200 iterations)\nBenchmarking collect_file_rows_10000: Analyzing\ncollect_file_rows_10000 time:   [37.002 ms 37.097 ms 37.197 ms]\n                        change: [+1.2704% +1.6254% +2.0358%] (p = 0.00 < 0.05)\n                        Performance has regressed.\nFound 1 outliers among 100 measurements (1.00%)\n  1 (1.00%) high severe\n\nBenchmarking collect_file_rows_10000_separate\nBenchmarking collect_file_rows_10000_separate: Warming up for 3.0000 s\nBenchmarking collect_file_rows_10000_separate: Collecting 100 samples in estimated 7.5040 s (200 iterations)\nBenchmarking collect_file_rows_10000_separate: Analyzing\ncollect_file_rows_10000_separate\n                        time:   [36.740 ms 36.859 ms 36.977 ms]\n                        change: [−20.295% −16.154% −11.805%] (p = 0.00 < 0.05)\n                        Performance has improved."
    },
    {
      "cmd": "cargo test",
      "status": "PASS",
      "log": "test snapshot_empty_module_report ... ok\ntest snapshot_file_rows_separate ... ok\ntest snapshot_lang_report_separate_shape ... ok\ntest snapshot_lang_report_top1 ... ok\ntest snapshot_lang_report_collapse_shape ... ok\ntest snapshot_module_report_shape ... ok\n\ntest result: ok. 9 passed; 0 failed; 0 ignored; 0 measured; 0 filtered out; finished in 0.21s\n\n   Doc-tests tokmd_model\n     Running `/home/jules/.rustup/toolchains/stable-x86_64-unknown-linux-gnu/bin/rustdoc --edition=2024 --crate-type lib --color auto --crate-name tokmd_model --test crates/tokmd-model/src/lib.rs --test-run-directory /app/crates/tokmd-model -L native=/app/target/debug/build/alloca-6c6af4dd8d7f698f/out --extern criterion=/app/target/debug/deps/libcriterion-a40f70c969dbe4d9.rlib --extern insta=/app/target/debug/deps/libinsta-9a0681082ad9a06e.rlib --extern proptest=/app/target/debug/deps/libproptest-5b58d1442badfd7c.rlib --extern serde=/app/target/debug/deps/libserde-ce6a36abbc92f71d.rlib --extern serde_json=/app/target/debug/deps/libserde_json-972a1480801fc63a.rlib --extern tempfile=/app/target/debug/deps/libtempfile-f51a2aafe76acb83.rlib --extern tokei=/app/target/debug/deps/libtokei-97bb319ad814eb5b.rlib --extern tokmd_model=/app/target/debug/deps/libtokmd_model-ccead8c340f4da3c.rlib --extern tokmd_module_key=/app/target/debug/deps/libtokmd_module_key-1e11ee2ab967eae0.rlib --extern tokmd_types=/app/target/debug/deps/libtokmd_types-ca15bbf54f1ec7d1.rlib -L dependency=/app/target/debug/deps -C embed-bitcode=no --check-cfg 'cfg(docsrs,test)' --check-cfg 'cfg(feature, values())' --error-format human`\n\nrunning 3 tests\ntest crates/tokmd-model/src/lib.rs - normalize_path (line 777) ... ok\ntest crates/tokmd-model/src/lib.rs - module_key (line 862) ... ok\ntest crates/tokmd-model/src/lib.rs - avg (line 752) ... ok\n\ntest result: ok. 3 passed; 0 failed; 0 ignored; 0 measured; 0 filtered out; finished in 0.00s\n\nall doctests ran in 0.51s; merged doctests compilation took 0.49s"
    },
    {
      "cmd": "cargo build",
      "status": "PASS",
      "log": "       Fresh tokmd-exclude v1.9.0 (/app/crates/tokmd-exclude)\n       Fresh tokmd-gate v1.9.0 (/app/crates/tokmd-gate)\n       Fresh clap_complete v4.6.0\n       Fresh tokmd-analysis-explain v1.9.0 (/app/crates/tokmd-analysis-explain)\n       Fresh tokmd-badge v1.9.0 (/app/crates/tokmd-badge)\n       Fresh tokmd-substrate v1.9.0 (/app/crates/tokmd-substrate)\n       Fresh base64 v0.22.1\n       Fresh tokmd-analysis-halstead v1.9.0 (/app/crates/tokmd-analysis-halstead)\n       Fresh tokmd-ffi-envelope v1.9.0 (/app/crates/tokmd-ffi-envelope)\n       Dirty tokmd v1.9.0 (/app/crates/tokmd): the dependency `tokmd-model` was rebuilt\n   Compiling tokmd v1.9.0 (/app/crates/tokmd)\n       Dirty tokmd-core v1.9.0 (/app/crates/tokmd-core): the dependency `tokmd-model` was rebuilt\n   Compiling tokmd-core v1.9.0 (/app/crates/tokmd-core)\n       Dirty tokmd-sensor v1.9.0 (/app/crates/tokmd-sensor): the dependency `tokmd-model` was rebuilt\n   Compiling tokmd-sensor v1.9.0 (/app/crates/tokmd-sensor)\n     Running `/home/jules/.rustup/toolchains/stable-x86_64-unknown-linux-gnu/bin/rustc --crate-name tokmd --edition=2024 crates/tokmd/src/lib.rs --error-format=json --json=diagnostic-rendered-ansi,artifacts,future-incompat --crate-type lib --emit=dep-info,metadata,link -C embed-bitcode=no -C debuginfo=2 --cfg 'feature=\"archetype\"' --cfg 'feature=\"content\"' --cfg 'feature=\"default\"' --cfg 'feature=\"fun\"' --cfg 'feature=\"git\"' --cfg 'feature=\"topics\"' --cfg 'feature=\"ui\"' --cfg 'feature=\"walk\"' --check-cfg 'cfg(docsrs,test)' --check-cfg 'cfg(feature, values(\"alias-tok\", \"archetype\", \"content\", \"default\", \"fun\", \"git\", \"topics\", \"ui\", \"walk\"))' -C metadata=2439a452d11f98e7 -C extra-filename=-4e32883fe1348d35 --out-dir /app/target/debug/deps -C incremental=/app/target/debug/incremental -L dependency=/app/target/debug/deps --extern anyhow=/app/target/debug/deps/libanyhow-1c897acad9a38b79.rmeta --extern blake3=/app/target/debug/deps/libblake3-ba57c91f91dea2f8.rmeta --extern clap=/app/target/debug/deps/libclap-4becc75c6d6358cd.rmeta --extern clap_complete=/app/target/debug/deps/libclap_complete-db4fc26ed995b904.rmeta --extern console=/app/target/debug/deps/libconsole-082fb92185463311.rmeta --extern dialoguer=/app/target/debug/deps/libdialoguer-21a6fbd0d024b082.rmeta --extern dirs=/app/target/debug/deps/libdirs-e2cb4f3a84b5aae4.rmeta --extern serde=/app/target/debug/deps/libserde-7b496471ddbe204c.rmeta --extern serde_json=/app/target/debug/deps/libserde_json-02554ac7efa4e2d5.rmeta --extern time=/app/target/debug/deps/libtime-ff5916d77934ff1e.rmeta --extern tokmd_analysis=/app/target/debug/deps/libtokmd_analysis-a100ab74b8f83e3f.rmeta --extern tokmd_analysis_explain=/app/target/debug/deps/libtokmd_analysis_explain-f555c7f62f539207.rmeta --extern tokmd_analysis_format=/app/target/debug/deps/libtokmd_analysis_format-fcd662b0a272e5cf.rmeta --extern tokmd_analysis_grid=/app/target/debug/deps/libtokmd_analysis_grid-b975859fd6ce769f.rmeta --extern tokmd_analysis_types=/app/target/debug/deps/libtokmd_analysis_types-a2119101128c1acf.rmeta --extern tokmd_badge=/app/target/debug/deps/libtokmd_badge-cea25afdb76d8de5.rmeta --extern tokmd_cockpit=/app/target/debug/deps/libtokmd_cockpit-cce84232adc64254.rmeta --extern tokmd_config=/app/target/debug/deps/libtokmd_config-996360d4ac8a6cfd.rmeta --extern tokmd_context_git=/app/target/debug/deps/libtokmd_context_git-b44d4dcb405a7dfa.rmeta --extern tokmd_context_policy=/app/target/debug/deps/libtokmd_context_policy-408c25833e79ac21.rmeta --extern tokmd_envelope=/app/target/debug/deps/libtokmd_envelope-f814661ecaa9d5a5.rmeta --extern tokmd_exclude=/app/target/debug/deps/libtokmd_exclude-4e503ec45eb7d506.rmeta --extern tokmd_export_tree=/app/target/debug/deps/libtokmd_export_tree-c1edb628bf303e61.rmeta --extern tokmd_format=/app/target/debug/deps/libtokmd_format-90b640945e61b2c1.rmeta --extern tokmd_gate=/app/target/debug/deps/libtokmd_gate-6bf8c0497d5f4a8d.rmeta --extern tokmd_git=/app/target/debug/deps/libtokmd_git-c7d6904f0b14a52f.rmeta --extern tokmd_model=/app/target/debug/deps/libtokmd_model-de4429ef2fd572ba.rmeta --extern tokmd_path=/app/target/debug/deps/libtokmd_path-7ed92164034bee00.rmeta --extern tokmd_progress=/app/target/debug/deps/libtokmd_progress-6493af3ed09d71d8.rmeta --extern tokmd_scan=/app/target/debug/deps/libtokmd_scan-c818da9d672267c5.rmeta --extern tokmd_settings=/app/target/debug/deps/libtokmd_settings-9edc796d5b2c7921.rmeta --extern tokmd_tokeignore=/app/target/debug/deps/libtokmd_tokeignore-cd4f92ff80c5d054.rmeta --extern tokmd_tool_schema=/app/target/debug/deps/libtokmd_tool_schema-43612909d26a540b.rmeta --extern tokmd_types=/app/target/debug/deps/libtokmd_types-1a256f6860a92825.rmeta --extern toml=/app/target/debug/deps/libtoml-416a762657a99d87.rmeta -L native=/app/target/debug/build/blake3-12e682763928d5d8/out -L native=/app/target/debug/build/blake3-12e682763928d5d8/out`\n     Running `/home/jules/.rustup/toolchains/stable-x86_64-unknown-linux-gnu/bin/rustc --crate-name tokmd_core --edition=2024 crates/tokmd-core/src/lib.rs --error-format=json --json=diagnostic-rendered-ansi,artifacts,future-incompat --crate-type lib --emit=dep-info,metadata,link -C embed-bitcode=no -C debuginfo=2 --cfg 'feature=\"default\"' --check-cfg 'cfg(docsrs,test)' --check-cfg 'cfg(feature, values(\"analysis\", \"cockpit\", \"default\", \"tokmd-analysis-types\"))' -C metadata=fa20c5b0243b991f -C extra-filename=-70e3e5a55ada1b60 --out-dir /app/target/debug/deps -C incremental=/app/target/debug/incremental -L dependency=/app/target/debug/deps --extern anyhow=/app/target/debug/deps/libanyhow-1c897acad9a38b79.rmeta --extern base64=/app/target/debug/deps/libbase64-5ec41e4236db44dc.rmeta --extern serde=/app/target/debug/deps/libserde-7b496471ddbe204c.rmeta --extern serde_json=/app/target/debug/deps/libserde_json-02554ac7efa4e2d5.rmeta --extern tokmd_config=/app/target/debug/deps/libtokmd_config-996360d4ac8a6cfd.rmeta --extern tokmd_format=/app/target/debug/deps/libtokmd_format-90b640945e61b2c1.rmeta --extern tokmd_model=/app/target/debug/deps/libtokmd_model-de4429ef2fd572ba.rmeta --extern tokmd_scan=/app/target/debug/deps/libtokmd_scan-c818da9d672267c5.rmeta --extern tokmd_scan_args=/app/target/debug/deps/libtokmd_scan_args-4084729957dff692.rmeta --extern tokmd_settings=/app/target/debug/deps/libtokmd_settings-9edc796d5b2c7921.rmeta --extern tokmd_types=/app/target/debug/deps/libtokmd_types-1a256f6860a92825.rmeta -L native=/app/target/debug/build/blake3-12e682763928d5d8/out -L native=/app/target/debug/build/blake3-12e682763928d5d8/out`\n     Running `/home/jules/.rustup/toolchains/stable-x86_64-unknown-linux-gnu/bin/rustc --crate-name tokmd_sensor --edition=2024 crates/tokmd-sensor/src/lib.rs --error-format=json --json=diagnostic-rendered-ansi,artifacts,future-incompat --crate-type lib --emit=dep-info,metadata,link -C embed-bitcode=no -C debuginfo=2 --cfg 'feature=\"default\"' --check-cfg 'cfg(docsrs,test)' --check-cfg 'cfg(feature, values(\"default\"))' -C metadata=db727498d8b25f96 -C extra-filename=-d305e98a22eeebca --out-dir /app/target/debug/deps -C incremental=/app/target/debug/incremental -L dependency=/app/target/debug/deps --extern anyhow=/app/target/debug/deps/libanyhow-1c897acad9a38b79.rmeta --extern serde=/app/target/debug/deps/libserde-7b496471ddbe204c.rmeta --extern tokmd_envelope=/app/target/debug/deps/libtokmd_envelope-f814661ecaa9d5a5.rmeta --extern tokmd_model=/app/target/debug/deps/libtokmd_model-de4429ef2fd572ba.rmeta --extern tokmd_scan=/app/target/debug/deps/libtokmd_scan-c818da9d672267c5.rmeta --extern tokmd_settings=/app/target/debug/deps/libtokmd_settings-9edc796d5b2c7921.rmeta --extern tokmd_substrate=/app/target/debug/deps/libtokmd_substrate-2a0628830ad77d63.rmeta --extern tokmd_types=/app/target/debug/deps/libtokmd_types-1a256f6860a92825.rmeta -L native=/app/target/debug/build/blake3-12e682763928d5d8/out -L native=/app/target/debug/build/blake3-12e682763928d5d8/out`\n     Running `/home/jules/.rustup/toolchains/stable-x86_64-unknown-linux-gnu/bin/rustc --crate-name tokmd --edition=2024 crates/tokmd/src/bin/tokmd.rs --error-format=json --json=diagnostic-rendered-ansi,artifacts,future-incompat --crate-type bin --emit=dep-info,link -C embed-bitcode=no -C debuginfo=2 --cfg 'feature=\"archetype\"' --cfg 'feature=\"content\"' --cfg 'feature=\"default\"' --cfg 'feature=\"fun\"' --cfg 'feature=\"git\"' --cfg 'feature=\"topics\"' --cfg 'feature=\"ui\"' --cfg 'feature=\"walk\"' --check-cfg 'cfg(docsrs,test)' --check-cfg 'cfg(feature, values(\"alias-tok\", \"archetype\", \"content\", \"default\", \"fun\", \"git\", \"topics\", \"ui\", \"walk\"))' -C metadata=7ed44a30fca95812 -C extra-filename=-4d89631356d65acc --out-dir /app/target/debug/deps -C incremental=/app/target/debug/incremental -L dependency=/app/target/debug/deps --extern anyhow=/app/target/debug/deps/libanyhow-1c897acad9a38b79.rlib --extern blake3=/app/target/debug/deps/libblake3-ba57c91f91dea2f8.rlib --extern clap=/app/target/debug/deps/libclap-4becc75c6d6358cd.rlib --extern clap_complete=/app/target/debug/deps/libclap_complete-db4fc26ed995b904.rlib --extern console=/app/target/debug/deps/libconsole-082fb92185463311.rlib --extern dialoguer=/app/target/debug/deps/libdialoguer-21a6fbd0d024b082.rlib --extern dirs=/app/target/debug/deps/libdirs-e2cb4f3a84b5aae4.rlib --extern serde=/app/target/debug/deps/libserde-7b496471ddbe204c.rlib --extern serde_json=/app/target/debug/deps/libserde_json-02554ac7efa4e2d5.rlib --extern time=/app/target/debug/deps/libtime-ff5916d77934ff1e.rlib --extern tokmd=/app/target/debug/deps/libtokmd-4e32883fe1348d35.rlib --extern tokmd_analysis=/app/target/debug/deps/libtokmd_analysis-a100ab74b8f83e3f.rlib --extern tokmd_analysis_explain=/app/target/debug/deps/libtokmd_analysis_explain-f555c7f62f539207.rlib --extern tokmd_analysis_format=/app/target/debug/deps/libtokmd_analysis_format-fcd662b0a272e5cf.rlib --extern tokmd_analysis_grid=/app/target/debug/deps/libtokmd_analysis_grid-b975859fd6ce769f.rlib --extern tokmd_analysis_types=/app/target/debug/deps/libtokmd_analysis_types-a2119101128c1acf.rlib --extern tokmd_badge=/app/target/debug/deps/libtokmd_badge-cea25afdb76d8de5.rlib --extern tokmd_cockpit=/app/target/debug/deps/libtokmd_cockpit-cce84232adc64254.rlib --extern tokmd_config=/app/target/debug/deps/libtokmd_config-996360d4ac8a6cfd.rlib --extern tokmd_context_git=/app/target/debug/deps/libtokmd_context_git-b44d4dcb405a7dfa.rlib --extern tokmd_context_policy=/app/target/debug/deps/libtokmd_context_policy-408c25833e79ac21.rlib --extern tokmd_envelope=/app/target/debug/deps/libtokmd_envelope-f814661ecaa9d5a5.rlib --extern tokmd_exclude=/app/target/debug/deps/libtokmd_exclude-4e503ec45eb7d506.rlib --extern tokmd_export_tree=/app/target/debug/deps/libtokmd_export_tree-c1edb628bf303e61.rlib --extern tokmd_format=/app/target/debug/deps/libtokmd_format-90b640945e61b2c1.rlib --extern tokmd_gate=/app/target/debug/deps/libtokmd_gate-6bf8c0497d5f4a8d.rlib --extern tokmd_git=/app/target/debug/deps/libtokmd_git-c7d6904f0b14a52f.rlib --extern tokmd_model=/app/target/debug/deps/libtokmd_model-de4429ef2fd572ba.rlib --extern tokmd_path=/app/target/debug/deps/libtokmd_path-7ed92164034bee00.rlib --extern tokmd_progress=/app/target/debug/deps/libtokmd_progress-6493af3ed09d71d8.rlib --extern tokmd_scan=/app/target/debug/deps/libtokmd_scan-c818da9d672267c5.rlib --extern tokmd_settings=/app/target/debug/deps/libtokmd_settings-9edc796d5b2c7921.rlib --extern tokmd_tokeignore=/app/target/debug/deps/libtokmd_tokeignore-cd4f92ff80c5d054.rlib --extern tokmd_tool_schema=/app/target/debug/deps/libtokmd_tool_schema-43612909d26a540b.rlib --extern tokmd_types=/app/target/debug/deps/libtokmd_types-1a256f6860a92825.rlib --extern toml=/app/target/debug/deps/libtoml-416a762657a99d87.rlib -L native=/app/target/debug/build/blake3-12e682763928d5d8/out -L native=/app/target/debug/build/blake3-12e682763928d5d8/out`\n    Finished `dev` profile [unoptimized + debuginfo] target(s) in 4.17s"
    },
    {
      "cmd": "cargo fmt",
      "status": "PASS",
      "log": "Diff in /app/crates/tokmd-model/benches/collect_bench.rs:1:\n\u001b[31m-use criterion::{criterion_group, criterion_main, Criterion};\n\u001b[m\u000f\u001b[32m+use criterion::{Criterion, criterion_group, criterion_main};\n\u001b[m\u000f use std::hint::black_box;\n use std::path::PathBuf;\n use tokei::{LanguageType, Languages, Report};\nDiff in /app/crates/tokmd-model/benches/collect_bench.rs:14:\n         rust_lang.reports.push(report);\n     }\n     langs.insert(LanguageType::Rust, rust_lang);\n\u001b[31m-    \n\u001b[m\u000f\u001b[32m+\n\u001b[m\u000f     let mut html_lang = tokei::Language::new();\n     for i in 0..5000 {\n         let name = PathBuf::from(format!(\"crates/foo/src/file_{i}.rs\"));\nDiff in /app/crates/tokmd-model/benches/collect_bench.rs:24:\n     langs.insert(LanguageType::Html, html_lang);\n     let module_roots = vec![\"crates\".to_string()];\n \n\u001b[31m-    c.bench_function(\"collect_file_rows_10000\", |b| b.iter(|| {\n\u001b[m\u000f\u001b[31m-        collect_file_rows(\n\u001b[m\u000f\u001b[31m-            black_box(&langs),\n\u001b[m\u000f\u001b[31m-            black_box(&module_roots),\n\u001b[m\u000f\u001b[31m-            black_box(2),\n\u001b[m\u000f\u001b[31m-            black_box(ChildIncludeMode::ParentsOnly),\n\u001b[m\u000f\u001b[31m-            black_box(None),\n\u001b[m\u000f\u001b[31m-        )\n\u001b[m\u000f\u001b[31m-    }));\n\u001b[m\u000f\u001b[31m-    \n\u001b[m\u000f\u001b[31m-    c.bench_function(\"collect_file_rows_10000_separate\", |b| b.iter(|| {\n\u001b[m\u000f\u001b[31m-        collect_file_rows(\n\u001b[m\u000f\u001b[31m-            black_box(&langs),\n\u001b[m\u000f\u001b[31m-            black_box(&module_roots),\n\u001b[m\u000f\u001b[31m-            black_box(2),\n\u001b[m\u000f\u001b[31m-            black_box(ChildIncludeMode::Separate),\n\u001b[m\u000f\u001b[31m-            black_box(None),\n\u001b[m\u000f\u001b[31m-        )\n\u001b[m\u000f\u001b[31m-    }));\n\u001b[m\u000f\u001b[32m+    c.bench_function(\"collect_file_rows_10000\", |b| {\n\u001b[m\u000f\u001b[32m+        b.iter(|| {\n\u001b[m\u000f\u001b[32m+            collect_file_rows(\n\u001b[m\u000f\u001b[32m+                black_box(&langs),\n\u001b[m\u000f\u001b[32m+                black_box(&module_roots),\n\u001b[m\u000f\u001b[32m+                black_box(2),\n\u001b[m\u000f\u001b[32m+                black_box(ChildIncludeMode::ParentsOnly),\n\u001b[m\u000f\u001b[32m+                black_box(None),\n\u001b[m\u000f\u001b[32m+            )\n\u001b[m\u000f\u001b[32m+        })\n\u001b[m\u000f\u001b[32m+    });\n\u001b[m\u000f\u001b[32m+\n\u001b[m\u000f\u001b[32m+    c.bench_function(\"collect_file_rows_10000_separate\", |b| {\n\u001b[m\u000f\u001b[32m+        b.iter(|| {\n\u001b[m\u000f\u001b[32m+            collect_file_rows(\n\u001b[m\u000f\u001b[32m+                black_box(&langs),\n\u001b[m\u000f\u001b[32m+                black_box(&module_roots),\n\u001b[m\u000f\u001b[32m+                black_box(2),\n\u001b[m\u000f\u001b[32m+                black_box(ChildIncludeMode::Separate),\n\u001b[m\u000f\u001b[32m+                black_box(None),\n\u001b[m\u000f\u001b[32m+            )\n\u001b[m\u000f\u001b[32m+        })\n\u001b[m\u000f\u001b[32m+    });\n\u001b[m\u000f }\n \n criterion_group!(benches, criterion_benchmark);\nDiff in /app/crates/tokmd-model/benches/normalize_path_bench.rs:1:\n\u001b[31m-use criterion::{criterion_group, criterion_main, Criterion};\n\u001b[m\u000f\u001b[31m-use std::path::Path;\n\u001b[m\u000f\u001b[32m+use criterion::{Criterion, criterion_group, criterion_main};\n\u001b[m\u000f use std::hint::black_box;\n\u001b[32m+use std::path::Path;\n\u001b[m\u000f use tokmd_model::normalize_path;\n \n fn criterion_benchmark(c: &mut Criterion) {\nDiff in /app/crates/tokmd-model/benches/normalize_path_bench.rs:9:\n     let p3 = Path::new(\"crates\\\\tokmd-model\\\\src\\\\lib.rs\");\n     let pref = Path::new(\"crates/tokmd-model\");\n     let pref2 = Path::new(\"./crates\");\n\u001b[31m-    \n\u001b[m\u000f\u001b[31m-    c.bench_function(\"normalize_path_clean\", |b| b.iter(|| normalize_path(black_box(p1), black_box(None))));\n\u001b[m\u000f\u001b[31m-    c.bench_function(\"normalize_path_dot_slash\", |b| b.iter(|| normalize_path(black_box(p2), black_box(None))));\n\u001b[m\u000f\u001b[31m-    c.bench_function(\"normalize_path_backslash\", |b| b.iter(|| normalize_path(black_box(p3), black_box(None))));\n\u001b[m\u000f\u001b[31m-    c.bench_function(\"normalize_path_with_prefix\", |b| b.iter(|| normalize_path(black_box(p1), black_box(Some(pref)))));\n\u001b[m\u000f\u001b[31m-    c.bench_function(\"normalize_path_with_dot_prefix\", |b| b.iter(|| normalize_path(black_box(p1), black_box(Some(pref2)))));\n\u001b[m\u000f\u001b[32m+\n\u001b[m\u000f\u001b[32m+    c.bench_function(\"normalize_path_clean\", |b| {\n\u001b[m\u000f\u001b[32m+        b.iter(|| normalize_path(black_box(p1), black_box(None)))\n\u001b[m\u000f\u001b[32m+    });\n\u001b[m\u000f\u001b[32m+    c.bench_function(\"normalize_path_dot_slash\", |b| {\n\u001b[m\u000f\u001b[32m+        b.iter(|| normalize_path(black_box(p2), black_box(None)))\n\u001b[m\u000f\u001b[32m+    });\n\u001b[m\u000f\u001b[32m+    c.bench_function(\"normalize_path_backslash\", |b| {\n\u001b[m\u000f\u001b[32m+        b.iter(|| normalize_path(black_box(p3), black_box(None)))\n\u001b[m\u000f\u001b[32m+    });\n\u001b[m\u000f\u001b[32m+    c.bench_function(\"normalize_path_with_prefix\", |b| {\n\u001b[m\u000f\u001b[32m+        b.iter(|| normalize_path(black_box(p1), black_box(Some(pref))))\n\u001b[m\u000f\u001b[32m+    });\n\u001b[m\u000f\u001b[32m+    c.bench_function(\"normalize_path_with_dot_prefix\", |b| {\n\u001b[m\u000f\u001b[32m+        b.iter(|| normalize_path(black_box(p1), black_box(Some(pref2))))\n\u001b[m\u000f\u001b[32m+    });\n\u001b[m\u000f }\n \n criterion_group!(benches, criterion_benchmark);\nDiff in /app/crates/tokmd-model/src/lib.rs:256:\n     config: &Config,\n ) -> Vec<FileRow> {\n     let mut map: BTreeMap<Key<'_>, (String, Agg)> = BTreeMap::new();\n\u001b[31m-    \n\u001b[m\u000f\u001b[32m+\n\u001b[m\u000f     let mut paths: Vec<String> = Vec::with_capacity(inputs.len());\n     for input in inputs {\n         paths.push(normalize_path(input.logical_path, None));\nDiff in /app/crates/tokmd-model/src/lib.rs:654:\n     strip_prefix: Option<&Path>,\n ) -> Vec<FileRow> {\n     let mut map: BTreeMap<Key<'_>, (String /*module*/, Agg)> = BTreeMap::new();\n\u001b[31m-    \n\u001b[m\u000f\u001b[32m+\n\u001b[m\u000f     // We create a single cache for the normalized paths so that each file is\n     // normalized only once, and we can safely borrow the strings for our `Key`s.\n     let mut path_cache: HashMap<&Path, String> = HashMap::new();\nDiff in /app/crates/tokmd-model/src/lib.rs:661:\n \n\u001b[31m-    // In a first pass, populate the path cache to avoid borrow checker issues \n\u001b[m\u000f\u001b[32m+    // In a first pass, populate the path cache to avoid borrow checker issues\n\u001b[m\u000f     // when looking up the cache during the BTreeMap inserts.\n     for (_lang_type, lang) in languages.iter() {\n         for report in &lang.reports {\nDiff in /app/crates/tokmd-model/src/lib.rs:682:\n     for (lang_type, lang) in languages.iter() {\n         for report in &lang.reports {\n             let path_ref = path_cache.get(report.name.as_path()).unwrap();\n\u001b[31m-                \n\u001b[m\u000f\u001b[32m+\n\u001b[m\u000f             let module = module_key_from_normalized(path_ref, module_roots, module_depth);\n             let st = report.stats.summarise();\n             let (bytes, tokens) = get_file_metrics(&report.name);\nDiff in /app/crates/tokmd-model/src/lib.rs:706:\n             for (child_type, reports) in &lang.children {\n                 for report in reports {\n                     let path_ref = path_cache.get(report.name.as_path()).unwrap();\n\u001b[31m-                        \n\u001b[m\u000f\u001b[32m+\n\u001b[m\u000f                     let module = module_key_from_normalized(path_ref, module_roots, module_depth);\n                     let st = report.stats.summarise();\n                     insert_row("
    },
    {
      "cmd": "cargo clippy",
      "status": "PASS",
      "log": "    Checking tokmd-model v1.9.0 (/app/crates/tokmd-model)\n    Checking tokmd v1.9.0 (/app/crates/tokmd)\n    Checking tokmd-sensor v1.9.0 (/app/crates/tokmd-sensor)\n    Checking tokmd-core v1.9.0 (/app/crates/tokmd-core)\n    Finished `dev` profile [unoptimized + debuginfo] target(s) in 1.49s"
    }
  ]
}
